README.rst
setup.cfg
setup.py
DesignSpark.Pmod.egg-info/PKG-INFO
DesignSpark.Pmod.egg-info/SOURCES.txt
DesignSpark.Pmod.egg-info/dependency_links.txt
DesignSpark.Pmod.egg-info/namespace_packages.txt
DesignSpark.Pmod.egg-info/requires.txt
DesignSpark.Pmod.egg-info/top_level.txt
DesignSpark/Pmod/ACL2.py
DesignSpark/Pmod/AD1.py
DesignSpark/Pmod/Error.py
DesignSpark/Pmod/GPS.py
DesignSpark/Pmod/HAT.py
DesignSpark/Pmod/HB3.py
DesignSpark/Pmod/ISNS20.py
DesignSpark/Pmod/KYPD.py
DesignSpark/Pmod/LS1.py
DesignSpark/Pmod/MIC3.py
DesignSpark/Pmod/OLEDrgb.py
DesignSpark/Pmod/SWT.py
DesignSpark/Pmod/TC1.py
DesignSpark/Pmod/__init__.py