Metadata-Version: 1.1
Name: DesignSpark.Pmod
Version: 0.3.0
Summary: Raspberry Pi Pmod HAT support library
Home-page: https://github.com/designsparkrs/DesignSpark.Pmod
Author: RS Components
Author-email: maint@abopen.com
License: MIT License
Download-URL: https://github.com/designsparkrs/DesignSpark.Pmod/archive/0.3.0.tar.gz
Keywords: raspberry pi raspi pmod digilent designspark spi pwm adc oled hbridge gps
Platform: UNKNOWN
Classifier: Development Status :: 4 - Beta
Classifier: Intended Audience :: Developers
Classifier: Intended Audience :: Education
Classifier: License :: OSI Approved :: MIT License
Classifier: Operating System :: POSIX :: Linux
Classifier: Programming Language :: Python :: 2
Classifier: Programming Language :: Python :: 2.7
Classifier: Programming Language :: Python :: 3
Classifier: Programming Language :: Python :: 3.4
Classifier: Programming Language :: Python :: 3.5
Classifier: Programming Language :: Python :: 3.6
Classifier: Programming Language :: Python :: 3.7
Classifier: Topic :: Education
Classifier: Topic :: System :: Hardware
Classifier: Topic :: System :: Hardware :: Hardware Drivers
